pytablewriter_altcol_theme/__init__.py
pytablewriter_altcol_theme/__version__.py
pytablewriter_altcol_theme/plugin.py
pytablewriter_altcol_theme-0.1.1.dist-info/LICENSE
pytablewriter_altcol_theme-0.1.1.dist-info/METADATA
pytablewriter_altcol_theme-0.1.1.dist-info/WHEEL
pytablewriter_altcol_theme-0.1.1.dist-info/top_level.txt
pytablewriter_altcol_theme-0.1.1.dist-info/RECORD
